ultrazoom/__init__.py
ultrazoom/control.py
ultrazoom/model.py
ultrazoom-0.2.1.dist-info/METADATA
ultrazoom-0.2.1.dist-info/WHEEL
ultrazoom-0.2.1.dist-info/top_level.txt
ultrazoom-0.2.1.dist-info/RECORD
