Metadata-Version: 2.4
Name: ultrazoom
Version: 0.2.1
Summary: A fast single image super-resolution (SISR) model for upscaling images with ultra high-quality.
Author: Andrew DalPino
License: MIT
Project-URL: Homepage, https://github.com/andrewdalpino/UltraZoom
Project-URL: Documentation, https://github.com/andrewdalpino/UltraZoom/README.md
Project-URL: Source, https://github.com/andrewdalpino/UltraZoom
Requires-Python: >=3.10
Requires-Dist: torch~=2.9.0
Requires-Dist: huggingface_hub~=0.34.0
Requires-Dist: safetensors~=0.4.3
Provides-Extra: dev
Requires-Dist: mypy; extra == "dev"
Requires-Dist: black; extra == "dev"
Requires-Dist: build; extra == "dev"
Requires-Dist: twine; extra == "dev"
Provides-Extra: test
Requires-Dist: mypy; extra == "test"
Requires-Dist: black; extra == "test"
